AiSummary/__init__.py
AiSummary/core.py
AiSummary-1.0.8.dist-info/LICENSE
AiSummary-1.0.8.dist-info/METADATA
AiSummary-1.0.8.dist-info/WHEEL
AiSummary-1.0.8.dist-info/top_level.txt
AiSummary-1.0.8.dist-info/RECORD
