Metadata-Version: 2.1
Name: AiSummary
Version: 1.0.8
Summary: Text summarization with Ai (without using API)
Author: Mohammad Taha Gorji
Author-email: MohammadTahaGorjiProfile@gmail.com
Classifier: Programming Language :: Python :: 3
Classifier: License :: OSI Approved :: MIT License
Classifier: Operating System :: OS Independent
Requires-Python: >=3.6
License-File: LICENSE
Requires-Dist: spacy
